{"assets/documents/privacy_policy.md":["assets/documents/privacy_policy.md"],"assets/images/bg.png":["assets/images/bg.png"],"assets/images/bg_light.png":["assets/images/bg_light.png"],"assets/images/bg_light_seamless.png":["assets/images/bg_light_seamless.png"],"assets/images/logo.png":["assets/images/logo.png"],"assets/images/logo_eposbinduptm.png":["assets/images/logo_eposbinduptm.png"],"assets/images/logo_germas.png":["assets/images/logo_germas.png"],"assets/images/logo_kemenkes.png":["assets/images/logo_kemenkes.png"],"assets/images/logo_puskesmas.png":["assets/images/logo_puskesmas.png"],"assets/images/logo_tabalong.png":["assets/images/logo_tabalong.png"],"assets/images/meja1_button.png":["assets/images/meja1_button.png"],"assets/images/meja2_button.png":["assets/images/meja2_button.png"],"assets/images/meja3_button.png":["assets/images/meja3_button.png"],"assets/images/meja4_button.png":["assets/images/meja4_button.png"],"assets/images/meja5_button.png":["assets/images/meja5_button.png"],"packages/cupertino_icons/assets/CupertinoIcons.ttf":["packages/cupertino_icons/assets/CupertinoIcons.ttf"]}